MANIFEST.in
README.rst
buildout.cfg
develop.cfg
requirements.txt
setup.py
version.txt
bob/__init__.py
bob.db.asvspoof2017.egg-info/PKG-INFO
bob.db.asvspoof2017.egg-info/SOURCES.txt
bob.db.asvspoof2017.egg-info/dependency_links.txt
bob.db.asvspoof2017.egg-info/entry_points.txt
bob.db.asvspoof2017.egg-info/not-zip-safe
bob.db.asvspoof2017.egg-info/requires.txt
bob.db.asvspoof2017.egg-info/top_level.txt
bob/db/__init__.py
bob/db/asvspoof2017/__init__.py
bob/db/asvspoof2017/checkfiles.py
bob/db/asvspoof2017/create.py
bob/db/asvspoof2017/driver.py
bob/db/asvspoof2017/dumplist.py
bob/db/asvspoof2017/models.py
bob/db/asvspoof2017/query.py
bob/db/asvspoof2017/test.py
bob/db/asvspoof2017/protocols/ASVspoof2017_dev.trl
bob/db/asvspoof2017/protocols/ASVspoof2017_eval.trl
bob/db/asvspoof2017/protocols/ASVspoof2017_train.trn
doc/conf.py
doc/index.rst