Metadata-Version: 1.1
Name: bob.db.asvspoof2017
Version: 1.1.0
Summary: ASVspoof2017 Database Access API for Bob
Home-page: http://gitlab.idiap.ch/bob/bob.db.asvspoof2017
Author: Pavel Korshunov
Author-email: pavel.korshunov@idiap.ch
License: BSD
Platform: UNKNOWN
Classifier: Framework :: Bob
Classifier: Development Status :: 4 - Beta
Classifier: Intended Audience :: Science/Research
Classifier: License :: OSI Approved :: BSD License
Classifier: Natural Language :: English
Classifier: Programming Language :: Python
Classifier: Programming Language :: Python :: 3
Classifier: Topic :: Scientific/Engineering :: Artificial Intelligence
Classifier: Topic :: Database :: Front-Ends
